neulang/__init__.py
neulang/__meta__.py
neulang/adapt_resolver.py
neulang/adapt_resolver_BACKUP_12640.py
neulang/adapt_resolver_BASE_12640.py
neulang/adapt_resolver_LOCAL_12640.py
neulang/adapt_resolver_REMOTE_12640.py
neulang/astir.py
neulang/base.py
neulang/callees.py
neulang/core.py
neulang/main.py
neulang/neudoc.py
neulang/omp.py
neulang/pubsub.py
neulang/resolvers.py
neulang/utils.py
tests/test_adapt_resolver.py
tests/test_base.py
tests/test_callees.py
tests/test_core.py
tests/test_main.py
tests/test_neudoc.py
tests/test_pubsub.py
tests/test_utils.py
neulang-0.3.2.dist-info/AUTHORS.rst
neulang-0.3.2.dist-info/LICENSE.md
neulang-0.3.2.dist-info/METADATA
neulang-0.3.2.dist-info/WHEEL
neulang-0.3.2.dist-info/entry_points.txt
neulang-0.3.2.dist-info/top_level.txt
neulang-0.3.2.dist-info/RECORD
