Metadata-Version: 2.1
Name: neulang
Version: 0.3.2
Summary: Executable org-formatted pseudocode embedded in Python.
Home-page: https://gitlab.com/skeledrew/neulang
Author: Andrew Phillips
Author-email: skeledrew@gmail.com
License: AGPLv3
Platform: any
Classifier: License :: OSI Approved :: GNU Affero General Public License v3 or later (AGPLv3+)
Classifier: Programming Language :: Python :: 3.7
Classifier: Intended Audience :: Developers
Classifier: Natural Language :: English
Classifier: Topic :: Software Development
Requires-Dist: docopt
Requires-Dist: adapt-parser
